{"code":0,"summary":{"cost":423060,"routes":17,"unassigned":0,"setup":0,"service":0,"duration":37993,"waiting_time":0,"priority":0,"violations":[],"computing_times":{"loading":3,"solving":1514}},"unassigned":[],"routes":[{"vehicle":1,"cost":56808,"setup":0,"service":0,"duration":5109,"waiting_time":0,"priority":0,"steps":[{"type":"start","location_index":0,"setup":0,"service":0,"waiting_time":0,"arrival":0,"duration":0,"violations":[]},{"type":"job","location_index":165,"id":1165,"setup":0,"service":0,"waiting_time":0,"job":1165,"arrival":1458,"duration":1458,"violations":[]},{"type":"job","location_index":145,"id":1145,"setup":0,"service":0,"waiting_time":0,"job":1145,"arrival":2327,"duration":2327,"violations":[]},{"type":"job","location_index":144,"id":1144,"setup":0,"service":0,"waiting_time":0,"job":1144,"arrival":2363,"duration":2363,"violations":[]},{"type":"job","location_index":151,"id":1151,"setup":0,"service":0,"waiting_time":0,"job":1151,"arrival":2563,"duration":2563,"violations":[]},{"type":"job","location_index":148,"id":1148,"setup":0,"service":0,"waiting_time":0,"job":1148,"arrival":2563,"duration":2563,"violations":[]},{"type":"job","location_index":150,"id":1150,"setup":0,"service":0,"waiting_time":0,"job":1150,"arrival":2727,"duration":2727,"violations":[]},{"type":"job","location_index":149,"id":1149,"setup":0,"service":0,"waiting_time":0,"job":1149,"arrival":2727,"duration":2727,"violations":[]},{"type":"job","location_index":146,"id":1146,"setup":0,"service":0,"waiting_time":0,"job":1146,"arrival":2727,"duration":2727,"violations":[]},{"type":"job","location_index":140,"id":1140,"setup":0,"service":0,"waiting_time":0,"job":1140,"arrival":2727,"duration":2727,"violations":[]},{"type":"job","location_index":170,"id":1170,"setup":0,"service":0,"waiting_time":0,"job":1170,"arrival":3621,"duration":3621,"violations":[]},{"type":"end","location_index":0,"setup":0,"service":0,"waiting_time":0,"arrival":5109,"duration":5109,"violations":[]}],"violations":[]},{"vehicle":2,"cost":59533,"setup":0,"service":0,"duration":5351,"waiting_time":0,"priority":0,"steps":[{"type":"start","location_index":0,"setup":0,"service":0,"waiting_time":0,"arrival":0,"duration":0,"violations":[]},{"type":"job","location_index":147,"id":1147,"setup":0,"service":0,"waiting_time":0,"job":1147,"arrival":2076,"duration":2076,"violations":[]},{"type":"job","location_index":143,"id":1143,"setup":0,"service":0,"waiting_time":0,"job":1143,"arrival":2197,"duration":2197,"violations":[]},{"type":"job","location_index":142,"id":1142,"setup":0,"service":0,"waiting_time":0,"job":1142,"arrival":2233,"duration":2233,"violations":[]},{"type":"job","location_index":141,"id":1141,"setup":0,"service":0,"waiting_time":0,"job":1141,"arrival":2749,"duration":2749,"violations":[]},{"type":"job","location_index":160,"id":1160,"setup":0,"service":0,"waiting_time":0,"job":1160,"arrival":3639,"duration":3639,"violations":[]},{"type":"job","location_index":168,"id":1168,"setup":0,"service":0,"waiting_time":0,"job":1168,"arrival":3903,"duration":3903,"violations":[]},{"type":"job","location_index":159,"id":1159,"setup":0,"service":0,"waiting_time":0,"job":1159,"arrival":3904,"duration":3904,"violations":[]},{"type":"job","location_index":169,"id":1169,"setup":0,"service":0,"waiting_time":0,"job":1169,"arrival":3971,"duration":3971,"violations":[]},{"type":"job","location_index":162,"id":1162,"setup":0,"service":0,"waiting_time":0,"job":1162,"arrival":3979,"duration":3979,"violations":[]},{"type":"job","location_index":164,"id":1164,"setup":0,"service":0,"waiting_time":0,"job":1164,"arrival":3988,"duration":3988,"violations":[]},{"type":"end","location_index":0,"setup":0,"service":0,"waiting_time":0,"arrival":5351,"duration":5351,"violations":[]}],"violations":[]},{"vehicle":3,"cost":37020,"setup":0,"service":0,"duration":3326,"waiting_time":0,"priority":0,"steps":[{"type":"start","location_index":0,"setup":0,"service":0,"waiting_time":0,"arrival":0,"duration":0,"violations":[]},{"type":"job","location_index":79,"id":1079,"setup":0,"service":0,"waiting_time":0,"job":1079,"arrival":876,"duration":876,"violations":[]},{"type":"job","location_index":155,"id":1155,"setup":0,"service":0,"waiting_time":0,"job":1155,"arrival":1384,"duration":1384,"violations":[]},{"type":"job","location_index":157,"id":1157,"setup":0,"service":0,"waiting_time":0,"job":1157,"arrival":1480,"duration":1480,"violations":[]},{"type":"job","location_index":154,"id":1154,"setup":0,"service":0,"waiting_time":0,"job":1154,"arrival":1585,"duration":1585,"violations":[]},{"type":"job","location_index":167,"id":1167,"setup":0,"service":0,"waiting_time":0,"job":1167,"arrival":1680,"duration":1680,"violations":[]},{"type":"job","location_index":161,"id":1161,"setup":0,"service":0,"waiting_time":0,"job":1161,"arrival":1710,"duration":1710,"violations":[]},{"type":"job","location_index":166,"id":1166,"setup":0,"service":0,"waiting_time":0,"job":1166,"arrival":1730,"duration":1730,"violations":[]},{"type":"job","location_index":163,"id":1163,"setup":0,"service":0,"waiting_time":0,"job":1163,"arrival":1738,"duration":1738,"violations":[]},{"type":"job","location_index":156,"id":1156,"setup":0,"service":0,"waiting_time":0,"job":1156,"arrival":2014,"duration":2014,"violations":[]},{"type":"job","location_index":57,"id":1057,"setup":0,"service":0,"waiting_time":0,"job":1057,"arrival":2267,"duration":2267,"violations":[]},{"type":"end","location_index":0,"setup":0,"service":0,"waiting_time":0,"arrival":3326,"duration":3326,"violations":[]}],"violations":[]},{"vehicle":4,"cost":29022,"setup":0,"service":0,"duration":2608,"waiting_time":0,"priority":0,"steps":[{"type":"start","location_index":0,"setup":0,"service":0,"waiting_time":0,"arrival":0,"duration":0,"violations":[]},{"type":"job","location_index":124,"id":1124,"setup":0,"service":0,"waiting_time":0,"job":1124,"arrival":1186,"duration":1186,"violations":[]},{"type":"job","location_index":136,"id":1136,"setup":0,"service":0,"waiting_time":0,"job":1136,"arrival":1186,"duration":1186,"violations":[]},{"type":"job","location_index":111,"id":1111,"setup":0,"service":0,"waiting_time":0,"job":1111,"arrival":1202,"duration":1202,"violations":[]},{"type":"job","location_index":134,"id":1134,"setup":0,"service":0,"waiting_time":0,"job":1134,"arrival":1215,"duration":1215,"violations":[]},{"type":"job","location_index":130,"id":1130,"setup":0,"service":0,"waiting_time":0,"job":1130,"arrival":1258,"duration":1258,"violations":[]},{"type":"job","location_index":114,"id":1114,"setup":0,"service":0,"waiting_time":0,"job":1114,"arrival":1293,"duration":1293,"violations":[]},{"type":"job","location_index":122,"id":1122,"setup":0,"service":0,"waiting_time":0,"job":1122,"arrival":1302,"duration":1302,"violations":[]},{"type":"job","location_index":118,"id":1118,"setup":0,"service":0,"waiting_time":0,"job":1118,"arrival":1313,"duration":1313,"violations":[]},{"type":"job","location_index":110,"id":1110,"setup":0,"service":0,"waiting_time":0,"job":1110,"arrival":1373,"duration":1373,"violations":[]},{"type":"job","location_index":107,"id":1107,"setup":0,"service":0,"waiting_time":0,"job":1107,"arrival":1692,"duration":1692,"violations":[]},{"type":"end","location_index":0,"setup":0,"service":0,"waiting_time":0,"arrival":2608,"duration":2608,"violations":[]}],"violations":[]},{"vehicle":5,"cost":28469,"setup":0,"service":0,"duration":2559,"waiting_time":0,"priority":0,"steps":[{"type":"start","location_index":0,"setup":0,"service":0,"waiting_time":0,"arrival":0,"duration":0,"violations":[]},{"type":"job","location_index":37,"id":1037,"setup":0,"service":0,"waiting_time":0,"job":1037,"arrival":157,"duration":157,"violations":[]},{"type":"job","location_index":40,"id":1040,"setup":0,"service":0,"waiting_time":0,"job":1040,"arrival":205,"duration":205,"violations":[]},{"type":"job","location_index":109,"id":1109,"setup":0,"service":0,"waiting_time":0,"job":1109,"arrival":1118,"duration":1118,"violations":[]},{"type":"job","location_index":121,"id":1121,"setup":0,"service":0,"waiting_time":0,"job":1121,"arrival":1174,"duration":1174,"violations":[]},{"type":"job","location_index":139,"id":1139,"setup":0,"service":0,"waiting_time":0,"job":1139,"arrival":1174,"duration":1174,"violations":[]},{"type":"job","location_index":120,"id":1120,"setup":0,"service":0,"waiting_time":0,"job":1120,"arrival":1174,"duration":1174,"violations":[]},{"type":"job","location_index":125,"id":1125,"setup":0,"service":0,"waiting_time":0,"job":1125,"arrival":1258,"duration":1258,"violations":[]},{"type":"job","location_index":119,"id":1119,"setup":0,"service":0,"waiting_time":0,"job":1119,"arrival":1258,"duration":1258,"violations":[]},{"type":"job","location_index":112,"id":1112,"setup":0,"service":0,"waiting_time":0,"job":1112,"arrival":1345,"duration":1345,"violations":[]},{"type":"job","location_index":117,"id":1117,"setup":0,"service":0,"waiting_time":0,"job":1117,"arrival":1458,"duration":1458,"violations":[]},{"type":"end","location_index":0,"setup":0,"service":0,"waiting_time":0,"arrival":2559,"duration":2559,"violations":[]}],"violations":[]},{"vehicle":6,"cost":20133,"setup":0,"service":0,"duration":1806,"waiting_time":0,"priority":0,"steps":[{"type":"start","location_index":0,"setup":0,"service":0,"waiting_time":0,"arrival":0,"duration":0,"violations":[]},{"type":"job","location_index":65,"id":1065,"setup":0,"service":0,"waiting_time":0,"job":1065,"arrival":777,"duration":777,"violations":[]},{"type":"job","location_index":71,"id":1071,"setup":0,"service":0,"waiting_time":0,"job":1071,"arrival":788,"duration":788,"violations":[]},{"type":"job","location_index":91,"id":1091,"setup":0,"service":0,"waiting_time":0,"job":1091,"arrival":794,"duration":794,"violations":[]},{"type":"job","location_index":75,"id":1075,"setup":0,"service":0,"waiting_time":0,"job":1075,"arrival":857,"duration":857,"violations":[]},{"type":"job","location_index":94,"id":1094,"setup":0,"service":0,"waiting_time":0,"job":1094,"arrival":912,"duration":912,"violations":[]},{"type":"job","location_index":80,"id":1080,"setup":0,"service":0,"waiting_time":0,"job":1080,"arrival":916,"duration":916,"violations":[]},{"type":"job","location_index":78,"id":1078,"setup":0,"service":0,"waiting_time":0,"job":1078,"arrival":930,"duration":930,"violations":[]},{"type":"job","location_index":62,"id":1062,"setup":0,"service":0,"waiting_time":0,"job":1062,"arrival":975,"duration":975,"violations":[]},{"type":"job","location_index":46,"id":1046,"setup":0,"service":0,"waiting_time":0,"job":1046,"arrival":1545,"duration":1545,"violations":[]},{"type":"job","location_index":1,"id":1001,"setup":0,"service":0,"waiting_time":0,"job":1001,"arrival":1645,"duration":1645,"violations":[]},{"type":"end","location_index":0,"setup":0,"service":0,"waiting_time":0,"arrival":1806,"duration":1806,"violations":[]}],"violations":[]},{"vehicle":7,"cost":27730,"setup":0,"service":0,"duration":2491,"waiting_time":0,"priority":0,"steps":[{"type":"start","location_index":0,"setup":0,"service":0,"waiting_time":0,"arrival":0,"duration":0,"violations":[]},{"type":"job","location_index":135,"id":1135,"setup":0,"service":0,"waiting_time":0,"job":1135,"arrival":1164,"duration":1164,"violations":[]},{"type":"job","location_index":127,"id":1127,"setup":0,"service":0,"waiting_time":0,"job":1127,"arrival":1180,"duration":1180,"violations":[]},{"type":"job","location_index":131,"id":1131,"setup":0,"service":0,"waiting_time":0,"job":1131,"arrival":1203,"duration":1203,"violations":[]},{"type":"job","location_index":116,"id":1116,"setup":0,"service":0,"waiting_time":0,"job":1116,"arrival":1208,"duration":1208,"violations":[]},{"type":"job","location_index":115,"id":1115,"setup":0,"service":0,"waiting_time":0,"job":1115,"arrival":1215,"duration":1215,"violations":[]},{"type":"job","location_index":138,"id":1138,"setup":0,"service":0,"waiting_time":0,"job":1138,"arrival":1217,"duration":1217,"violations":[]},{"type":"job","location_index":128,"id":1128,"setup":0,"service":0,"waiting_time":0,"job":1128,"arrival":1217,"duration":1217,"violations":[]},{"type":"job","location_index":132,"id":1132,"setup":0,"service":0,"waiting_time":0,"job":1132,"arrival":1217,"duration":1217,"violations":[]},{"type":"job","location_index":133,"id":1133,"setup":0,"service":0,"waiting_time":0,"job":1133,"arrival":1295,"duration":1295,"violations":[]},{"type":"job","location_index":20,"id":1020,"setup":0,"service":0,"waiting_time":0,"job":1020,"arrival":2251,"duration":2251,"violations":[]},{"type":"end","location_index":0,"setup":0,"service":0,"waiting_time":0,"arrival":2491,"duration":2491,"violations":[]}],"violations":[]},{"vehicle":8,"cost":20894,"setup":0,"service":0,"duration":1875,"waiting_time":0,"priority":0,"steps":[{"type":"start","location_index":0,"setup":0,"service":0,"waiting_time":0,"arrival":0,"duration":0,"violations":[]},{"type":"job","location_index":96,"id":1096,"setup":0,"service":0,"waiting_time":0,"job":1096,"arrival":894,"duration":894,"violations":[]},{"type":"job","location_index":100,"id":1100,"setup":0,"service":0,"waiting_time":0,"job":1100,"arrival":896,"duration":896,"violations":[]},{"type":"job","location_index":95,"id":1095,"setup":0,"service":0,"waiting_time":0,"job":1095,"arrival":897,"duration":897,"violations":[]},{"type":"job","location_index":126,"id":1126,"setup":0,"service":0,"waiting_time":0,"job":1126,"arrival":900,"duration":900,"violations":[]},{"type":"job","location_index":137,"id":1137,"setup":0,"service":0,"waiting_time":0,"job":1137,"arrival":904,"duration":904,"violations":[]},{"type":"job","location_index":97,"id":1097,"setup":0,"service":0,"waiting_time":0,"job":1097,"arrival":905,"duration":905,"violations":[]},{"type":"job","location_index":103,"id":1103,"setup":0,"service":0,"waiting_time":0,"job":1103,"arrival":932,"duration":932,"violations":[]},{"type":"job","location_index":98,"id":1098,"setup":0,"service":0,"waiting_time":0,"job":1098,"arrival":963,"duration":963,"violations":[]},{"type":"job","location_index":102,"id":1102,"setup":0,"service":0,"waiting_time":0,"job":1102,"arrival":967,"duration":967,"violations":[]},{"type":"job","location_index":113,"id":1113,"setup":0,"service":0,"waiting_time":0,"job":1113,"arrival":967,"duration":967,"violations":[]},{"type":"end","location_index":0,"setup":0,"service":0,"waiting_time":0,"arrival":1875,"duration":1875,"violations":[]}],"violations":[]},{"vehicle":9,"cost":27766,"setup":0,"service":0,"duration":2494,"waiting_time":0,"priority":0,"steps":[{"type":"start","location_index":0,"setup":0,"service":0,"waiting_time":0,"arrival":0,"duration":0,"violations":[]},{"type":"job","location_index":66,"id":1066,"setup":0,"service":0,"waiting_time":0,"job":1066,"arrival":849,"duration":849,"violations":[]},{"type":"job","location_index":84,"id":1084,"setup":0,"service":0,"waiting_time":0,"job":1084,"arrival":886,"duration":886,"violations":[]},{"type":"job","location_index":90,"id":1090,"setup":0,"service":0,"waiting_time":0,"job":1090,"arrival":897,"duration":897,"violations":[]},{"type":"job","location_index":74,"id":1074,"setup":0,"service":0,"waiting_time":0,"job":1074,"arrival":903,"duration":903,"violations":[]},{"type":"job","location_index":92,"id":1092,"setup":0,"service":0,"waiting_time":0,"job":1092,"arrival":917,"duration":917,"violations":[]},{"type":"job","location_index":53,"id":1053,"setup":0,"service":0,"waiting_time":0,"job":1053,"arrival":1141,"duration":1141,"violations":[]},{"type":"job","location_index":47,"id":1047,"setup":0,"service":0,"waiting_time":0,"job":1047,"arrival":1754,"duration":1754,"violations":[]},{"type":"job","location_index":153,"id":1153,"setup":0,"service":0,"waiting_time":0,"job":1153,"arrival":2096,"duration":2096,"violations":[]},{"type":"job","location_index":152,"id":1152,"setup":0,"service":0,"waiting_time":0,"job":1152,"arrival":2096,"duration":2096,"violations":[]},{"type":"job","location_index":12,"id":1012,"setup":0,"service":0,"waiting_time":0,"job":1012,"arrival":2176,"duration":2176,"violations":[]},{"type":"end","location_index":0,"setup":0,"service":0,"waiting_time":0,"arrival":2494,"duration":2494,"violations":[]}],"violations":[]},{"vehicle":10,"cost":20391,"setup":0,"service":0,"duration":1831,"waiting_time":0,"priority":0,"steps":[{"type":"start","location_index":0,"setup":0,"service":0,"waiting_time":0,"arrival":0,"duration":0,"violations":[]},{"type":"job","location_index":89,"id":1089,"setup":0,"service":0,"waiting_time":0,"job":1089,"arrival":868,"duration":868,"violations":[]},{"type":"job","location_index":93,"id":1093,"setup":0,"service":0,"waiting_time":0,"job":1093,"arrival":875,"duration":875,"violations":[]},{"type":"job","location_index":73,"id":1073,"setup":0,"service":0,"waiting_time":0,"job":1073,"arrival":875,"duration":875,"violations":[]},{"type":"job","location_index":83,"id":1083,"setup":0,"service":0,"waiting_time":0,"job":1083,"arrival":875,"duration":875,"violations":[]},{"type":"job","location_index":81,"id":1081,"setup":0,"service":0,"waiting_time":0,"job":1081,"arrival":875,"duration":875,"violations":[]},{"type":"job","location_index":77,"id":1077,"setup":0,"service":0,"waiting_time":0,"job":1077,"arrival":882,"duration":882,"violations":[]},{"type":"job","location_index":52,"id":1052,"setup":0,"service":0,"waiting_time":0,"job":1052,"arrival":905,"duration":905,"violations":[]},{"type":"job","location_index":87,"id":1087,"setup":0,"service":0,"waiting_time":0,"job":1087,"arrival":994,"duration":994,"violations":[]},{"type":"job","location_index":49,"id":1049,"setup":0,"service":0,"waiting_time":0,"job":1049,"arrival":994,"duration":994,"violations":[]},{"type":"job","location_index":58,"id":1058,"setup":0,"service":0,"waiting_time":0,"job":1058,"arrival":994,"duration":994,"violations":[]},{"type":"end","location_index":0,"setup":0,"service":0,"waiting_time":0,"arrival":1831,"duration":1831,"violations":[]}],"violations":[]},{"vehicle":11,"cost":21573,"setup":0,"service":0,"duration":1936,"waiting_time":0,"priority":0,"steps":[{"type":"start","location_index":0,"setup":0,"service":0,"waiting_time":0,"arrival":0,"duration":0,"violations":[]},{"type":"job","location_index":48,"id":1048,"setup":0,"service":0,"waiting_time":0,"job":1048,"arrival":568,"duration":568,"violations":[]},{"type":"job","location_index":14,"id":1014,"setup":0,"service":0,"waiting_time":0,"job":1014,"arrival":570,"duration":570,"violations":[]},{"type":"job","location_index":129,"id":1129,"setup":0,"service":0,"waiting_time":0,"job":1129,"arrival":943,"duration":943,"violations":[]},{"type":"job","location_index":99,"id":1099,"setup":0,"service":0,"waiting_time":0,"job":1099,"arrival":961,"duration":961,"violations":[]},{"type":"job","location_index":123,"id":1123,"setup":0,"service":0,"waiting_time":0,"job":1123,"arrival":976,"duration":976,"violations":[]},{"type":"job","location_index":108,"id":1108,"setup":0,"service":0,"waiting_time":0,"job":1108,"arrival":994,"duration":994,"violations":[]},{"type":"job","location_index":104,"id":1104,"setup":0,"service":0,"waiting_time":0,"job":1104,"arrival":1008,"duration":1008,"violations":[]},{"type":"job","location_index":101,"id":1101,"setup":0,"service":0,"waiting_time":0,"job":1101,"arrival":1011,"duration":1011,"violations":[]},{"type":"job","location_index":106,"id":1106,"setup":0,"service":0,"waiting_time":0,"job":1106,"arrival":1036,"duration":1036,"violations":[]},{"type":"job","location_index":105,"id":1105,"setup":0,"service":0,"waiting_time":0,"job":1105,"arrival":1047,"duration":1047,"violations":[]},{"type":"end","location_index":0,"setup":0,"service":0,"waiting_time":0,"arrival":1936,"duration":1936,"violations":[]}],"violations":[]},{"vehicle":12,"cost":20241,"setup":0,"service":0,"duration":1816,"waiting_time":0,"priority":0,"steps":[{"type":"start","location_index":0,"setup":0,"service":0,"waiting_time":0,"arrival":0,"duration":0,"violations":[]},{"type":"job","location_index":55,"id":1055,"setup":0,"service":0,"waiting_time":0,"job":1055,"arrival":866,"duration":866,"violations":[]},{"type":"job","location_index":56,"id":1056,"setup":0,"service":0,"waiting_time":0,"job":1056,"arrival":866,"duration":866,"violations":[]},{"type":"job","location_index":85,"id":1085,"setup":0,"service":0,"waiting_time":0,"job":1085,"arrival":869,"duration":869,"violations":[]},{"type":"job","location_index":59,"id":1059,"setup":0,"service":0,"waiting_time":0,"job":1059,"arrival":875,"duration":875,"violations":[]},{"type":"job","location_index":76,"id":1076,"setup":0,"service":0,"waiting_time":0,"job":1076,"arrival":875,"duration":875,"violations":[]},{"type":"job","location_index":64,"id":1064,"setup":0,"service":0,"waiting_time":0,"job":1064,"arrival":886,"duration":886,"violations":[]},{"type":"job","location_index":68,"id":1068,"setup":0,"service":0,"waiting_time":0,"job":1068,"arrival":917,"duration":917,"violations":[]},{"type":"job","location_index":69,"id":1069,"setup":0,"service":0,"waiting_time":0,"job":1069,"arrival":929,"duration":929,"violations":[]},{"type":"job","location_index":51,"id":1051,"setup":0,"service":0,"waiting_time":0,"job":1051,"arrival":933,"duration":933,"violations":[]},{"type":"job","location_index":72,"id":1072,"setup":0,"service":0,"waiting_time":0,"job":1072,"arrival":934,"duration":934,"violations":[]},{"type":"end","location_index":0,"setup":0,"service":0,"waiting_time":0,"arrival":1816,"duration":1816,"violations":[]}],"violations":[]},{"vehicle":13,"cost":8755,"setup":0,"service":0,"duration":782,"waiting_time":0,"priority":0,"steps":[{"type":"start","location_index":0,"setup":0,"service":0,"waiting_time":0,"arrival":0,"duration":0,"violations":[]},{"type":"job","location_index":3,"id":1003,"setup":0,"service":0,"waiting_time":0,"job":1003,"arrival":178,"duration":178,"violations":[]},{"type":"job","location_index":30,"id":1030,"setup":0,"service":0,"waiting_time":0,"job":1030,"arrival":283,"duration":283,"violations":[]},{"type":"job","location_index":45,"id":1045,"setup":0,"service":0,"waiting_time":0,"job":1045,"arrival":315,"duration":315,"violations":[]},{"type":"job","location_index":19,"id":1019,"setup":0,"service":0,"waiting_time":0,"job":1019,"arrival":352,"duration":352,"violations":[]},{"type":"job","location_index":13,"id":1013,"setup":0,"service":0,"waiting_time":0,"job":1013,"arrival":402,"duration":402,"violations":[]},{"type":"job","location_index":2,"id":1002,"setup":0,"service":0,"waiting_time":0,"job":1002,"arrival":431,"duration":431,"violations":[]},{"type":"job","location_index":6,"id":1006,"setup":0,"service":0,"waiting_time":0,"job":1006,"arrival":448,"duration":448,"violations":[]},{"type":"job","location_index":11,"id":1011,"setup":0,"service":0,"waiting_time":0,"job":1011,"arrival":468,"duration":468,"violations":[]},{"type":"job","location_index":25,"id":1025,"setup":0,"service":0,"waiting_time":0,"job":1025,"arrival":510,"duration":510,"violations":[]},{"type":"job","location_index":9,"id":1009,"setup":0,"service":0,"waiting_time":0,"job":1009,"arrival":534,"duration":534,"violations":[]},{"type":"end","location_index":0,"setup":0,"service":0,"waiting_time":0,"arrival":782,"duration":782,"violations":[]}],"violations":[]},{"vehicle":14,"cost":10869,"setup":0,"service":0,"duration":973,"waiting_time":0,"priority":0,"steps":[{"type":"start","location_index":0,"setup":0,"service":0,"waiting_time":0,"arrival":0,"duration":0,"violations":[]},{"type":"job","location_index":158,"id":1158,"setup":0,"service":0,"waiting_time":0,"job":1158,"arrival":108,"duration":108,"violations":[]},{"type":"job","location_index":28,"id":1028,"setup":0,"service":0,"waiting_time":0,"job":1028,"arrival":344,"duration":344,"violations":[]},{"type":"job","location_index":29,"id":1029,"setup":0,"service":0,"waiting_time":0,"job":1029,"arrival":417,"duration":417,"violations":[]},{"type":"job","location_index":18,"id":1018,"setup":0,"service":0,"waiting_time":0,"job":1018,"arrival":458,"duration":458,"violations":[]},{"type":"job","location_index":5,"id":1005,"setup":0,"service":0,"waiting_time":0,"job":1005,"arrival":505,"duration":505,"violations":[]},{"type":"job","location_index":27,"id":1027,"setup":0,"service":0,"waiting_time":0,"job":1027,"arrival":543,"duration":543,"violations":[]},{"type":"job","location_index":22,"id":1022,"setup":0,"service":0,"waiting_time":0,"job":1022,"arrival":575,"duration":575,"violations":[]},{"type":"job","location_index":39,"id":1039,"setup":0,"service":0,"waiting_time":0,"job":1039,"arrival":605,"duration":605,"violations":[]},{"type":"job","location_index":26,"id":1026,"setup":0,"service":0,"waiting_time":0,"job":1026,"arrival":642,"duration":642,"violations":[]},{"type":"job","location_index":15,"id":1015,"setup":0,"service":0,"waiting_time":0,"job":1015,"arrival":728,"duration":728,"violations":[]},{"type":"end","location_index":0,"setup":0,"service":0,"waiting_time":0,"arrival":973,"duration":973,"violations":[]}],"violations":[]},{"vehicle":15,"cost":8910,"setup":0,"service":0,"duration":797,"waiting_time":0,"priority":0,"steps":[{"type":"start","location_index":0,"setup":0,"service":0,"waiting_time":0,"arrival":0,"duration":0,"violations":[]},{"type":"job","location_index":31,"id":1031,"setup":0,"service":0,"waiting_time":0,"job":1031,"arrival":154,"duration":154,"violations":[]},{"type":"job","location_index":10,"id":1010,"setup":0,"service":0,"waiting_time":0,"job":1010,"arrival":278,"duration":278,"violations":[]},{"type":"job","location_index":21,"id":1021,"setup":0,"service":0,"waiting_time":0,"job":1021,"arrival":355,"duration":355,"violations":[]},{"type":"job","location_index":7,"id":1007,"setup":0,"service":0,"waiting_time":0,"job":1007,"arrival":369,"duration":369,"violations":[]},{"type":"job","location_index":17,"id":1017,"setup":0,"service":0,"waiting_time":0,"job":1017,"arrival":465,"duration":465,"violations":[]},{"type":"job","location_index":24,"id":1024,"setup":0,"service":0,"waiting_time":0,"job":1024,"arrival":508,"duration":508,"violations":[]},{"type":"job","location_index":41,"id":1041,"setup":0,"service":0,"waiting_time":0,"job":1041,"arrival":568,"duration":568,"violations":[]},{"type":"job","location_index":23,"id":1023,"setup":0,"service":0,"waiting_time":0,"job":1023,"arrival":582,"duration":582,"violations":[]},{"type":"job","location_index":4,"id":1004,"setup":0,"service":0,"waiting_time":0,"job":1004,"arrival":605,"duration":605,"violations":[]},{"type":"job","location_index":44,"id":1044,"setup":0,"service":0,"waiting_time":0,"job":1044,"arrival":614,"duration":614,"violations":[]},{"type":"end","location_index":0,"setup":0,"service":0,"waiting_time":0,"arrival":797,"duration":797,"violations":[]}],"violations":[]},{"vehicle":16,"cost":4716,"setup":0,"service":0,"duration":423,"waiting_time":0,"priority":0,"steps":[{"type":"start","location_index":0,"setup":0,"service":0,"waiting_time":0,"arrival":0,"duration":0,"violations":[]},{"type":"job","location_index":42,"id":1042,"setup":0,"service":0,"waiting_time":0,"job":1042,"arrival":201,"duration":201,"violations":[]},{"type":"job","location_index":33,"id":1033,"setup":0,"service":0,"waiting_time":0,"job":1033,"arrival":201,"duration":201,"violations":[]},{"type":"job","location_index":16,"id":1016,"setup":0,"service":0,"waiting_time":0,"job":1016,"arrival":204,"duration":204,"violations":[]},{"type":"job","location_index":8,"id":1008,"setup":0,"service":0,"waiting_time":0,"job":1008,"arrival":204,"duration":204,"violations":[]},{"type":"job","location_index":32,"id":1032,"setup":0,"service":0,"waiting_time":0,"job":1032,"arrival":211,"duration":211,"violations":[]},{"type":"job","location_index":43,"id":1043,"setup":0,"service":0,"waiting_time":0,"job":1043,"arrival":211,"duration":211,"violations":[]},{"type":"job","location_index":38,"id":1038,"setup":0,"service":0,"waiting_time":0,"job":1038,"arrival":211,"duration":211,"violations":[]},{"type":"job","location_index":36,"id":1036,"setup":0,"service":0,"waiting_time":0,"job":1036,"arrival":211,"duration":211,"violations":[]},{"type":"job","location_index":35,"id":1035,"setup":0,"service":0,"waiting_time":0,"job":1035,"arrival":211,"duration":211,"violations":[]},{"type":"job","location_index":34,"id":1034,"setup":0,"service":0,"waiting_time":0,"job":1034,"arrival":211,"duration":211,"violations":[]},{"type":"end","location_index":0,"setup":0,"service":0,"waiting_time":0,"arrival":423,"duration":423,"violations":[]}],"violations":[]},{"vehicle":17,"cost":20230,"setup":0,"service":0,"duration":1816,"waiting_time":0,"priority":0,"steps":[{"type":"start","location_index":0,"setup":0,"service":0,"waiting_time":0,"arrival":0,"duration":0,"violations":[]},{"type":"job","location_index":50,"id":1050,"setup":0,"service":0,"waiting_time":0,"job":1050,"arrival":819,"duration":819,"violations":[]},{"type":"job","location_index":61,"id":1061,"setup":0,"service":0,"waiting_time":0,"job":1061,"arrival":859,"duration":859,"violations":[]},{"type":"job","location_index":63,"id":1063,"setup":0,"service":0,"waiting_time":0,"job":1063,"arrival":868,"duration":868,"violations":[]},{"type":"job","location_index":70,"id":1070,"setup":0,"service":0,"waiting_time":0,"job":1070,"arrival":889,"duration":889,"violations":[]},{"type":"job","location_index":67,"id":1067,"setup":0,"service":0,"waiting_time":0,"job":1067,"arrival":899,"duration":899,"violations":[]},{"type":"job","location_index":86,"id":1086,"setup":0,"service":0,"waiting_time":0,"job":1086,"arrival":900,"duration":900,"violations":[]},{"type":"job","location_index":88,"id":1088,"setup":0,"service":0,"waiting_time":0,"job":1088,"arrival":907,"duration":907,"violations":[]},{"type":"job","location_index":82,"id":1082,"setup":0,"service":0,"waiting_time":0,"job":1082,"arrival":915,"duration":915,"violations":[]},{"type":"job","location_index":54,"id":1054,"setup":0,"service":0,"waiting_time":0,"job":1054,"arrival":960,"duration":960,"violations":[]},{"type":"job","location_index":60,"id":1060,"setup":0,"service":0,"waiting_time":0,"job":1060,"arrival":990,"duration":990,"violations":[]},{"type":"end","location_index":0,"setup":0,"service":0,"waiting_time":0,"arrival":1816,"duration":1816,"violations":[]}],"violations":[]}]}